{
  "dct_title_s": "Purdue Campus map [Indiana--West Lafayette] {1906}",
  "dct_alternative_sm": [
    "Purdue Campus: West Lafayette, Indiana, 1906"
  ],
  "dct_description_sm": [
    "Map of the Purdue University Campus in 1906 showing buildings, building names, roads, paths, and other features."
  ],
  "dct_language_sm": [
    "eng"
  ],
  "dct_publisher_sm": [
    "Purdue University Libraries"
  ],
  "schema_provider_s": "Purdue University",
  "gbl_resourceClass_sm": [
    "Maps"
  ],
  "dct_subject_sm": [
    "Purdue University--Buildings",
    "Universities & colleges--Indiana--West Lafayette"
  ],
  "dcat_keyword_sm": [
    "Universities",
    "Campuses",
    "Purdue Georeferenced Imagery"
  ],
  "dct_temporal_sm": [
    "1906"
  ],
  "dct_issued_s": "1906",
  "gbl_indexYear_im": [
    "1906"
  ],
  "gbl_dateRange_drsim": [
    "[1906 TO 1906]"
  ],
  "dct_spatial_sm": [
    "Indiana--West Lafayette",
    "Indiana"
  ],
  "locn_geometry": "POLYGON((-86.918 40.432, -86.910 40.432, -86.910 40.423, -86.918 40.423, -86.918 40.432))",
  "dcat_bbox": "ENVELOPE(-86.918,-86.910,40.432,40.423)",
  "dcat_centroid": "40.4275,-86.914",
  "pcdm_memberOf_sm": [
    "64bd8c4c-8e60-4956-b43d-bdc3f93db488"
  ],
  "dct_isPartOf_sm": [
    "09d-02"
  ],
  "dct_replaces_sm": [
    "fb419ad0-cacd-4dee-a342-e28ce6a06c6e"
  ],
  "dct_rightsHolder_sm": [
    "Purdue University"
  ],
  "dct_accessRights_s": "Public",
  "dct_format_s": "GeoTIFF",
  "gbl_fileSize_s": "90.6 MB",
  "dct_references_s": "{\"http://lccn.loc.gov/sh85035852\":\"https://collections.lib.purdue.edu/campus/about\",\"http://schema.org/downloadUrl\":[{\"url\":\"https://mapsweb.lib.purdue.edu/datasets/HistoricCampus/1906.tif.zip\",\"label\":\"GeoTIFF\"}],\"https://github.com/cogeotiff/cog-spec\":\"https://geobtaa-assets-prod.s3.us-east-2.amazonaws.com/store/asset/c7c88bac-df34-42bc-9616-0ba196745879/360168d2aa244bf2f0578e4e4199757c.tif\"}",
  "id": "b1g_09d_2WSxn7jIdy1i",
  "gbl_mdVersion_s": "Aardvark"
}